uvtask/__init__.py
uvtask/__main__.py
uvtask/cli.py
uvtask/colors.py
uvtask/commands.py
uvtask/config.py
uvtask/executor.py
uvtask/formatters.py
uvtask/hooks.py
uvtask/parser.py
uvtask/py.typed
uvtask-0.7.0.dist-info/WHEEL
uvtask-0.7.0.dist-info/entry_points.txt
uvtask-0.7.0.dist-info/METADATA
uvtask-0.7.0.dist-info/RECORD
