Metadata-Version: 2.3
Name: uvtask
Version: 0.7.0
Summary: An extremely fast Python task runner.
Keywords: uv,uvx,scripts,tool,pyproject,task,runner
Author: ticdenis
Author-email: ticdenis <navarrodenis940503@outlook.com>
License: MIT
Classifier: Intended Audience :: Information Technology
Classifier: Intended Audience :: System Administrators
Classifier: Operating System :: OS Independent
Classifier: Programming Language :: Python :: 3
Classifier: Programming Language :: Python
Classifier: Topic :: Software Development :: Libraries :: Python Modules
Classifier: Topic :: Software Development :: Libraries
Classifier: Topic :: Software Development
Classifier: Typing :: Typed
Classifier: Development Status :: 4 - Beta
Classifier: Intended Audience :: Developers
Classifier: License :: OSI Approved :: MIT License
Classifier: Programming Language :: Python :: 3 :: Only
Classifier: Programming Language :: Python :: 3.13
Classifier: Programming Language :: Python :: 3.14
Maintainer: ticdenis
Maintainer-email: ticdenis <navarrodenis940503@outlook.com>
Requires-Python: >=3.13
Project-URL: documentation, https://github.com/aiopy/python-uvtask/README.md
Project-URL: repository, https://github.com/aiopy/python-uvtask
